DbtAlchemy/DbtPy.py
DbtAlchemy/__init__.py
DbtAlchemy/base.py
DbtAlchemy/pyodbc.py
DbtAlchemy/reflection.py
DbtAlchemy/requirements.py
DbtAlchemy-1.0.1.1.dist-info/LICENSE
DbtAlchemy-1.0.1.1.dist-info/METADATA
DbtAlchemy-1.0.1.1.dist-info/WHEEL
DbtAlchemy-1.0.1.1.dist-info/entry_points.txt
DbtAlchemy-1.0.1.1.dist-info/top_level.txt
DbtAlchemy-1.0.1.1.dist-info/RECORD
