Metadata-Version: 2.1
Name: DbtAlchemy
Version: 1.0.1.1
Summary: SQLAlchemy support for GBase 8s Servers
Home-page: https://gbasedbt.com
Author: Development Team
Author-email: dbt@gbasebdt.com
License: Apache License 2.0
Keywords: sqlalchemy database interface for GBase 8s servers
Platform: All
Classifier: Development Status :: 4 - Beta
Classifier: Intended Audience :: Developers
Classifier: License :: OSI Approved :: Apache Software License
Classifier: Operating System :: OS Independent
Classifier: Topic :: Database :: Front-Ends
Requires-Dist: sqlalchemy (<2.0,>=0.7.3)
Requires-Dist: typing-extensions (<3.10)
Requires-Dist: DbtPy (>=3.0.3)
